actuator/__init__.py
actuator/agent.py
actuator/scheduler.py
volttron_actuator-0.1.1a8.dist-info/entry_points.txt
volttron_actuator-0.1.1a8.dist-info/LICENSE
volttron_actuator-0.1.1a8.dist-info/WHEEL
volttron_actuator-0.1.1a8.dist-info/METADATA
volttron_actuator-0.1.1a8.dist-info/RECORD
