Metadata-Version: 2.1
Name: volttron-actuator
Version: 0.1.1a8
Summary: The Actuator Agent is used to manage write access to devices. Other agents may request scheduled times, called Tasks, to interact with one or more devices.
Home-page: https://github.com/VOLTTRON/volttron-actuator
License: Apache-2.0
Author: Mark Bonicillo
Author-email: volttron@pnnl.gov
Requires-Python: >=3.10,<4.0
Classifier: Intended Audience :: Developers
Classifier: Intended Audience :: Information Technology
Classifier: Intended Audience :: Other Audience
Classifier: Intended Audience :: Science/Research
Classifier: License :: OSI Approved :: Apache Software License
Classifier: Programming Language :: Python :: 3
Classifier: Programming Language :: Python :: 3.10
Classifier: Programming Language :: Python :: 3.11
Classifier: Programming Language :: Python :: 3 :: Only
Requires-Dist: types-tzlocal (>=4.2.2.2,<5.0.0.0)
Requires-Dist: tzlocal (>=4.2,<5.0)
Requires-Dist: volttron (>=10.0.4rc1,<11.0)
Project-URL: Repository, https://github.com/VOLTTRON/volttron-actuator
